README
setup.py
pygoogleearth/__init__.py
pygoogleearth/animationcontroller.py
pygoogleearth/camerainfo.py
pygoogleearth/featurecollection.py
pygoogleearth/geapplication.py
pygoogleearth/getime.py
pygoogleearth/kml.py
pygoogleearth/rpcserver.py
pygoogleearth/searchcontroller.py
pygoogleearth/tourcontroller.py
pygoogleearth/viewextents.py
pygoogleearth.egg-info/PKG-INFO
pygoogleearth.egg-info/SOURCES.txt
pygoogleearth.egg-info/dependency_links.txt
pygoogleearth.egg-info/requires.txt
pygoogleearth.egg-info/top_level.txt